python_databases/__init__.py
python_databases/elasticsearch_infrastructure/__init__.py
python_databases/elasticsearch_infrastructure/elasticsearch.py
python_databases/postgresql_infrastructure/__init__.py
python_databases/postgresql_infrastructure/postgresql.py
python_databases-0.1.6.dist-info/licenses/LICENSE
python_databases-0.1.6.dist-info/METADATA
python_databases-0.1.6.dist-info/WHEEL
python_databases-0.1.6.dist-info/top_level.txt
python_databases-0.1.6.dist-info/RECORD
